Metadata-Version: 2.1
Name: strdtm
Version: 0.0.1
Summary: Handeling strings in datetime
Home-page: UNKNOWN
Author-email: ranjitmaity95@gmail.com
License: UNKNOWN
Platform: UNKNOWN
